pypardiso/__init__.py
pypardiso/pardiso_wrapper.py
pypardiso/scipy_aliases.py
pypardiso-0.4.6.dist-info/LICENSE.txt
pypardiso-0.4.6.dist-info/METADATA
pypardiso-0.4.6.dist-info/WHEEL
pypardiso-0.4.6.dist-info/top_level.txt
pypardiso-0.4.6.dist-info/RECORD
