Metadata-Version: 2.1
Name: pypardiso
Version: 0.4.6
Summary: Python interface to the Intel MKL Pardiso library to solve large sparse linear systems of equations
Author: Adrian Haas
License: Copyright (c) 2016, Adrian Haas and ETH Zürich
Project-URL: Homepage, https://github.com/haasad/PyPardiso
Project-URL: Repository, https://github.com/haasad/PyPardiso.git
Project-URL: Changelog, https://github.com/haasad/PyPardiso/releases
Keywords: pardiso,sparse solver
Classifier: Programming Language :: Python :: 3
Classifier: Topic :: Scientific/Engineering :: Mathematics
Requires-Python: >=3.8
License-File: LICENSE.txt
Requires-Dist: mkl!=2024.0
Requires-Dist: numpy
Requires-Dist: scipy
